<?xml version='1.0' encoding='utf-8'?>
<lkf>
    <advanced_options>
        <active>True</active>
        <folio>
            <config>False</config>
            <manual>False</manual>
            <required>False</required>
        </folio>
    </advanced_options>
    <allow_page_navigation>True</allow_page_navigation>
    <confirmation>
        <button_message>Mandar respuestas</button_message>
        <message>¡Su información fue capturada!</message>
        <redirect_url>default</redirect_url>
    </confirmation>
    <created_at>1662570786.0</created_at>
    <description />
    <edit_public_records>False</edit_public_records>
    <edit_registers>True</edit_registers>
    <element_ids>[]</element_ids>
    <email_configuration>
        <body />
        <email_fields>[]</email_fields>
        <emails>[]</emails>
        <embed_company_picture>False</embed_company_picture>
        <embed_fields>[]</embed_fields>
        <pdf_template>{}</pdf_template>
        <reply_to>None</reply_to>
        <resend>DONT_RESEND</resend>
        <send_attachments>False</send_attachments>
        <send_pdf>False</send_pdf>
        <sender>None</sender>
        <subject />
        <template_html>None</template_html>
        <templates>[]</templates>
        <timer_config>None</timer_config>
    </email_configuration>
    <emails>[]</emails>
    <enable_geolocation>True</enable_geolocation>
    <enable_versions>True</enable_versions>
    <force_owner_logo>True</force_owner_logo>
    <form_pages>
        <item>
            <page_description>None</page_description>
            <page_fields>
                <item>
                    <affecting_rules>[]</affecting_rules>
                    <buttons_ids>[]</buttons_ids>
                    <catalog>None</catalog>
                    <catalog_fields>[]</catalog_fields>
                    <catalog_relation>None</catalog_relation>
                    <default>False</default>
                    <default_value />
                    <descriptor>None</descriptor>
                    <fav>False</fav>
                    <field_id>6318d13144b1e9292d39b8b5</field_id>
                    <field_type>group</field_type>
                    <grading_criteria>{}</grading_criteria>
                    <group>None</group>
                    <groups_fields>
                        <item>6318d157e7dc26b52f2c4293</item>
                        <item>6318d2136217e6d71339b8c1</item>
                        <item>6318d2136217e6d71339b8c2</item>
                        <item>6318d2136217e6d71339b8c3</item>
                    </groups_fields>
                    <help_text>None</help_text>
                    <label>Razón Social</label>
                    <number_type>None</number_type>
                    <options>[]</options>
                    <properties>
                        <body_payload>[]</body_payload>
                        <color />
                        <comment />
                        <custom />
                        <elements_ids>[]</elements_ids>
                        <email_configuration>None</email_configuration>
                        <enable_barcode>None</enable_barcode>
                        <fieldId>[]</fieldId>
                        <file_name />
                        <file_name_array>[]</file_name_array>
                        <help_text>False</help_text>
                        <icon>{}</icon>
                        <image_origin>None</image_origin>
                        <input_parameter>[]</input_parameter>
                        <max>0</max>
                        <max_images_count>5</max_images_count>
                        <metadata>[]</metadata>
                        <method />
                        <mime_types>[]</mime_types>
                        <min>0</min>
                        <min_images_count>0</min_images_count>
                        <multi_selection>False</multi_selection>
                        <notification>{}</notification>
                        <number_of_decimals>2</number_of_decimals>
                        <openChoice>False</openChoice>
                        <parameters>[]</parameters>
                        <pfd_print>always</pfd_print>
                        <pfd_style>Tabla_respuestas</pfd_style>
                        <selected>None</selected>
                        <send_email>False</send_email>
                        <send_record>False</send_record>
                        <send_to_lkf>False</send_to_lkf>
                        <service_name />
                        <update_values>{}</update_values>
                        <url />
                        <username>False</username>
                        <visible_on />
                        <wait_response>False</wait_response>
                        <watermark_config>None</watermark_config>
                        <watermark_enable>False</watermark_enable>
                    </properties>
                    <required>False</required>
                    <rules>[]</rules>
                    <show_for_rule>True</show_for_rule>
                    <validations>{}</validations>
                    <visible>True</visible>
                </item>
                <item>
                    <affecting_rules>[]</affecting_rules>
                    <buttons_ids>[]</buttons_ids>
                    <catalog>None</catalog>
                    <catalog_fields>[]</catalog_fields>
                    <catalog_relation>None</catalog_relation>
                    <default>False</default>
                    <default_value />
                    <descriptor>None</descriptor>
                    <fav>False</fav>
                    <field_id>6318d2dc0d37da73390c3d1d</field_id>
                    <field_type>group</field_type>
                    <grading_criteria>{}</grading_criteria>
                    <group>None</group>
                    <groups_fields>
                        <item>6318d363a76a4d7dd439b87b</item>
                        <item>6318d363a76a4d7dd439b87c</item>
                        <item>632a46ea2e282c04a572186c</item>
                        <item>632a46ea2e282c04a572186b</item>
                        <item>6318d363a76a4d7dd439b87d</item>
                        <item>6475297f252ea20a2916a9d5</item>
                    </groups_fields>
                    <help_text>None</help_text>
                    <label>Validaciones Adicionales desde XML</label>
                    <number_type>None</number_type>
                    <options>[]</options>
                    <properties>
                        <body_payload>[]</body_payload>
                        <color />
                        <comment />
                        <custom />
                        <elements_ids>[]</elements_ids>
                        <email_configuration>None</email_configuration>
                        <enable_barcode>None</enable_barcode>
                        <fieldId>[]</fieldId>
                        <file_name />
                        <file_name_array>[]</file_name_array>
                        <help_text>False</help_text>
                        <icon>{}</icon>
                        <image_origin>None</image_origin>
                        <input_parameter>[]</input_parameter>
                        <max>0</max>
                        <max_images_count>5</max_images_count>
                        <metadata>[]</metadata>
                        <method />
                        <mime_types>[]</mime_types>
                        <min>0</min>
                        <min_images_count>0</min_images_count>
                        <multi_selection>False</multi_selection>
                        <notification>{}</notification>
                        <number_of_decimals>2</number_of_decimals>
                        <openChoice>False</openChoice>
                        <parameters>[]</parameters>
                        <pfd_print>always</pfd_print>
                        <pfd_style>Tabla_respuestas</pfd_style>
                        <selected>None</selected>
                        <send_email>False</send_email>
                        <send_record>False</send_record>
                        <send_to_lkf>False</send_to_lkf>
                        <service_name />
                        <update_values>{}</update_values>
                        <url />
                        <username>False</username>
                        <visible_on />
                        <wait_response>False</wait_response>
                        <watermark_config>None</watermark_config>
                        <watermark_enable>False</watermark_enable>
                    </properties>
                    <required>False</required>
                    <rules>[]</rules>
                    <show_for_rule>True</show_for_rule>
                    <validations>{}</validations>
                    <visible>True</visible>
                </item>
                <item>
                    <affecting_rules>[]</affecting_rules>
                    <buttons_ids>[]</buttons_ids>
                    <catalog>None</catalog>
                    <catalog_fields>[]</catalog_fields>
                    <catalog_relation>None</catalog_relation>
                    <default>False</default>
                    <default_value />
                    <descriptor>None</descriptor>
                    <fav>False</fav>
                    <field_id>631f4f0248743cdd01fe4b6c</field_id>
                    <field_type>radio</field_type>
                    <grading_criteria>{}</grading_criteria>
                    <group>None</group>
                    <groups_fields>[]</groups_fields>
                    <help_text>None</help_text>
                    <label>Activo</label>
                    <number_type>None</number_type>
                    <options>
                        <item>
                            <label>Sí</label>
                            <points>None</points>
                            <selected>False</selected>
                            <value>sí</value>
                        </item>
                        <item>
                            <label>No</label>
                            <points>None</points>
                            <selected>False</selected>
                            <value>no</value>
                        </item>
                    </options>
                    <properties>
                        <body_payload>[]</body_payload>
                        <color />
                        <comment />
                        <custom>0</custom>
                        <elements_ids>[]</elements_ids>
                        <email_configuration>None</email_configuration>
                        <enable_barcode>None</enable_barcode>
                        <fieldId>[]</fieldId>
                        <file_name />
                        <file_name_array>[]</file_name_array>
                        <help_text>False</help_text>
                        <icon>{}</icon>
                        <image_origin>None</image_origin>
                        <input_parameter>[]</input_parameter>
                        <max>None</max>
                        <max_images_count>5</max_images_count>
                        <metadata>[]</metadata>
                        <method />
                        <mime_types>[]</mime_types>
                        <min>None</min>
                        <min_images_count>0</min_images_count>
                        <multi_selection>False</multi_selection>
                        <notification>{}</notification>
                        <number_of_decimals>2</number_of_decimals>
                        <openChoice>False</openChoice>
                        <parameters>[]</parameters>
                        <pfd_print>always</pfd_print>
                        <pfd_style>Tabla_respuestas</pfd_style>
                        <selected>None</selected>
                        <send_email>False</send_email>
                        <send_record>False</send_record>
                        <send_to_lkf>False</send_to_lkf>
                        <service_name />
                        <update_values>{}</update_values>
                        <url />
                        <username>False</username>
                        <visible_on />
                        <wait_response>False</wait_response>
                        <watermark_config>None</watermark_config>
                        <watermark_enable>False</watermark_enable>
                    </properties>
                    <required>False</required>
                    <rules>[]</rules>
                    <show_for_rule>True</show_for_rule>
                    <validations>{}</validations>
                    <visible>True</visible>
                </item>
                <item>
                    <affecting_rules>[]</affecting_rules>
                    <buttons_ids>[]</buttons_ids>
                    <catalog>None</catalog>
                    <catalog_fields>[]</catalog_fields>
                    <catalog_relation>None</catalog_relation>
                    <default>False</default>
                    <default_value />
                    <descriptor>None</descriptor>
                    <fav>False</fav>
                    <field_id>6491f61eb2e38c03b8398a18</field_id>
                    <field_type>radio</field_type>
                    <grading_criteria>{}</grading_criteria>
                    <group>None</group>
                    <groups_fields>[]</groups_fields>
                    <help_text>None</help_text>
                    <label>Validación General</label>
                    <number_type>None</number_type>
                    <options>
                        <item>
                            <label>Sí</label>
                            <points>None</points>
                            <selected>False</selected>
                            <value>sí</value>
                        </item>
                        <item>
                            <label>No</label>
                            <points>None</points>
                            <selected>False</selected>
                            <value>no</value>
                        </item>
                    </options>
                    <properties>
                        <body_payload>[]</body_payload>
                        <color />
                        <comment />
                        <custom>0</custom>
                        <elements_ids>[]</elements_ids>
                        <email_configuration>None</email_configuration>
                        <enable_barcode>None</enable_barcode>
                        <fieldId>[]</fieldId>
                        <file_name />
                        <file_name_array>[]</file_name_array>
                        <help_text>False</help_text>
                        <icon>{}</icon>
                        <image_origin>None</image_origin>
                        <input_parameter>[]</input_parameter>
                        <max>None</max>
                        <max_images_count>5</max_images_count>
                        <metadata>[]</metadata>
                        <method />
                        <mime_types>[]</mime_types>
                        <min>None</min>
                        <min_images_count>0</min_images_count>
                        <multi_selection>False</multi_selection>
                        <notification>{}</notification>
                        <number_of_decimals>2</number_of_decimals>
                        <openChoice>False</openChoice>
                        <parameters>[]</parameters>
                        <pfd_print>always</pfd_print>
                        <pfd_style>Tabla_respuestas</pfd_style>
                        <selected>None</selected>
                        <send_email>False</send_email>
                        <send_record>False</send_record>
                        <send_to_lkf>False</send_to_lkf>
                        <service_name />
                        <update_values>{}</update_values>
                        <url />
                        <username>False</username>
                        <visible_on />
                        <wait_response>False</wait_response>
                        <watermark_config>None</watermark_config>
                        <watermark_enable>False</watermark_enable>
                    </properties>
                    <required>False</required>
                    <rules>[]</rules>
                    <show_for_rule>True</show_for_rule>
                    <validations>{}</validations>
                    <visible>True</visible>
                </item>
                <item>
                    <affecting_rules>[]</affecting_rules>
                    <buttons_ids>[]</buttons_ids>
                    <catalog>None</catalog>
                    <catalog_fields>[]</catalog_fields>
                    <catalog_relation>None</catalog_relation>
                    <default>False</default>
                    <default_value />
                    <descriptor>None</descriptor>
                    <fav>False</fav>
                    <field_id>6318d363a76a4d7dd439b87b</field_id>
                    <field_type>text</field_type>
                    <grading_criteria>{}</grading_criteria>
                    <group>
                        <group_id>6318d2dc0d37da73390c3d1d</group_id>
                        <group_set_id>0</group_set_id>
                    </group>
                    <groups_fields>[]</groups_fields>
                    <help_text>None</help_text>
                    <label>Nombre del Tag en el XML</label>
                    <number_type>None</number_type>
                    <options>[]</options>
                    <properties>
                        <body_payload>[]</body_payload>
                        <color />
                        <comment />
                        <custom />
                        <elements_ids>[]</elements_ids>
                        <email_configuration>None</email_configuration>
                        <enable_barcode>None</enable_barcode>
                        <fieldId>[]</fieldId>
                        <file_name />
                        <file_name_array>[]</file_name_array>
                        <help_text>False</help_text>
                        <icon>{}</icon>
                        <image_origin>None</image_origin>
                        <input_parameter>[]</input_parameter>
                        <max>None</max>
                        <max_images_count>5</max_images_count>
                        <metadata>[]</metadata>
                        <method />
                        <mime_types>[]</mime_types>
                        <min>None</min>
                        <min_images_count>0</min_images_count>
                        <multi_selection>False</multi_selection>
                        <notification>{}</notification>
                        <number_of_decimals>2</number_of_decimals>
                        <openChoice>False</openChoice>
                        <parameters>[]</parameters>
                        <pfd_print>always</pfd_print>
                        <pfd_style>Tabla_respuestas</pfd_style>
                        <selected>None</selected>
                        <send_email>False</send_email>
                        <send_record>False</send_record>
                        <send_to_lkf>False</send_to_lkf>
                        <service_name />
                        <update_values>{}</update_values>
                        <url />
                        <username>False</username>
                        <visible_on />
                        <wait_response>False</wait_response>
                        <watermark_config>None</watermark_config>
                        <watermark_enable>False</watermark_enable>
                    </properties>
                    <required>True</required>
                    <rules>[]</rules>
                    <show_for_rule>True</show_for_rule>
                    <validations>{}</validations>
                    <visible>True</visible>
                </item>
                <item>
                    <affecting_rules>[]</affecting_rules>
                    <buttons_ids>[]</buttons_ids>
                    <catalog>None</catalog>
                    <catalog_fields>[]</catalog_fields>
                    <catalog_relation>None</catalog_relation>
                    <default>False</default>
                    <default_value />
                    <descriptor>None</descriptor>
                    <fav>False</fav>
                    <field_id>6318d363a76a4d7dd439b87c</field_id>
                    <field_type>textarea</field_type>
                    <grading_criteria>{}</grading_criteria>
                    <group>
                        <group_id>6318d2dc0d37da73390c3d1d</group_id>
                        <group_set_id>0</group_set_id>
                    </group>
                    <groups_fields>[]</groups_fields>
                    <help_text>None</help_text>
                    <label>Valores Aceptados</label>
                    <number_type>None</number_type>
                    <options>[]</options>
                    <properties>
                        <body_payload>[]</body_payload>
                        <color />
                        <comment />
                        <custom />
                        <elements_ids>[]</elements_ids>
                        <email_configuration>None</email_configuration>
                        <enable_barcode>None</enable_barcode>
                        <fieldId>[]</fieldId>
                        <file_name />
                        <file_name_array>[]</file_name_array>
                        <help_text>False</help_text>
                        <icon>{}</icon>
                        <image_origin>None</image_origin>
                        <input_parameter>[]</input_parameter>
                        <max>None</max>
                        <max_images_count>5</max_images_count>
                        <metadata>[]</metadata>
                        <method />
                        <mime_types>[]</mime_types>
                        <min>None</min>
                        <min_images_count>0</min_images_count>
                        <multi_selection>False</multi_selection>
                        <notification>{}</notification>
                        <number_of_decimals>2</number_of_decimals>
                        <openChoice>False</openChoice>
                        <parameters>[]</parameters>
                        <pfd_print>always</pfd_print>
                        <pfd_style>Tabla_respuestas</pfd_style>
                        <selected>None</selected>
                        <send_email>False</send_email>
                        <send_record>False</send_record>
                        <send_to_lkf>False</send_to_lkf>
                        <service_name />
                        <update_values>{}</update_values>
                        <url />
                        <username>False</username>
                        <visible_on />
                        <wait_response>False</wait_response>
                        <watermark_config>None</watermark_config>
                        <watermark_enable>False</watermark_enable>
                    </properties>
                    <required>True</required>
                    <rules>[]</rules>
                    <show_for_rule>True</show_for_rule>
                    <validations>{}</validations>
                    <visible>True</visible>
                </item>
                <item>
                    <affecting_rules>[]</affecting_rules>
                    <buttons_ids>[]</buttons_ids>
                    <catalog>None</catalog>
                    <catalog_fields>[]</catalog_fields>
                    <catalog_relation>None</catalog_relation>
                    <default>False</default>
                    <default_value />
                    <descriptor>None</descriptor>
                    <fav>False</fav>
                    <field_id>632a46ea2e282c04a572186c</field_id>
                    <field_type>radio</field_type>
                    <grading_criteria>{}</grading_criteria>
                    <group>
                        <group_id>6318d2dc0d37da73390c3d1d</group_id>
                        <group_set_id>0</group_set_id>
                    </group>
                    <groups_fields>[]</groups_fields>
                    <help_text>None</help_text>
                    <label>Razón Social donde aplica</label>
                    <number_type>None</number_type>
                    <options>
                        <item>
                            <label>IACON</label>
                            <points>None</points>
                            <selected>False</selected>
                            <value>iacon</value>
                        </item>
                        <item>
                            <label>REDES</label>
                            <points>None</points>
                            <selected>False</selected>
                            <value>redes</value>
                        </item>
                    </options>
                    <properties>
                        <body_payload>[]</body_payload>
                        <color />
                        <comment />
                        <custom />
                        <elements_ids>[]</elements_ids>
                        <email_configuration>None</email_configuration>
                        <enable_barcode>None</enable_barcode>
                        <fieldId>[]</fieldId>
                        <file_name />
                        <file_name_array>[]</file_name_array>
                        <help_text>False</help_text>
                        <icon>{}</icon>
                        <image_origin>None</image_origin>
                        <input_parameter>[]</input_parameter>
                        <max>None</max>
                        <max_images_count>5</max_images_count>
                        <metadata>[]</metadata>
                        <method />
                        <mime_types>[]</mime_types>
                        <min>None</min>
                        <min_images_count>0</min_images_count>
                        <multi_selection>False</multi_selection>
                        <notification>{}</notification>
                        <number_of_decimals>2</number_of_decimals>
                        <openChoice>False</openChoice>
                        <parameters>[]</parameters>
                        <pfd_print>always</pfd_print>
                        <pfd_style>Tabla_respuestas</pfd_style>
                        <selected>None</selected>
                        <send_email>False</send_email>
                        <send_record>False</send_record>
                        <send_to_lkf>False</send_to_lkf>
                        <service_name />
                        <update_values>{}</update_values>
                        <url />
                        <username>False</username>
                        <visible_on />
                        <wait_response>False</wait_response>
                        <watermark_config>None</watermark_config>
                        <watermark_enable>False</watermark_enable>
                    </properties>
                    <required>True</required>
                    <rules>[]</rules>
                    <show_for_rule>True</show_for_rule>
                    <validations>{}</validations>
                    <visible>True</visible>
                </item>
                <item>
                    <affecting_rules>[]</affecting_rules>
                    <buttons_ids>[]</buttons_ids>
                    <catalog>None</catalog>
                    <catalog_fields>[]</catalog_fields>
                    <catalog_relation>None</catalog_relation>
                    <default>False</default>
                    <default_value />
                    <descriptor>None</descriptor>
                    <fav>False</fav>
                    <field_id>632a46ea2e282c04a572186b</field_id>
                    <field_type>textarea</field_type>
                    <grading_criteria>{}</grading_criteria>
                    <group>
                        <group_id>6318d2dc0d37da73390c3d1d</group_id>
                        <group_set_id>0</group_set_id>
                    </group>
                    <groups_fields>[]</groups_fields>
                    <help_text>None</help_text>
                    <label>Observaciones</label>
                    <number_type>None</number_type>
                    <options>[]</options>
                    <properties>
                        <body_payload>[]</body_payload>
                        <color />
                        <comment />
                        <custom />
                        <elements_ids>[]</elements_ids>
                        <email_configuration>None</email_configuration>
                        <enable_barcode>None</enable_barcode>
                        <fieldId>[]</fieldId>
                        <file_name />
                        <file_name_array>[]</file_name_array>
                        <help_text>False</help_text>
                        <icon>{}</icon>
                        <image_origin>None</image_origin>
                        <input_parameter>[]</input_parameter>
                        <max>None</max>
                        <max_images_count>5</max_images_count>
                        <metadata>[]</metadata>
                        <method />
                        <mime_types>[]</mime_types>
                        <min>None</min>
                        <min_images_count>0</min_images_count>
                        <multi_selection>False</multi_selection>
                        <notification>{}</notification>
                        <number_of_decimals>2</number_of_decimals>
                        <openChoice>False</openChoice>
                        <parameters>[]</parameters>
                        <pfd_print>always</pfd_print>
                        <pfd_style>Tabla_respuestas</pfd_style>
                        <selected>None</selected>
                        <send_email>False</send_email>
                        <send_record>False</send_record>
                        <send_to_lkf>False</send_to_lkf>
                        <service_name />
                        <update_values>{}</update_values>
                        <url />
                        <username>False</username>
                        <visible_on />
                        <wait_response>False</wait_response>
                        <watermark_config>None</watermark_config>
                        <watermark_enable>False</watermark_enable>
                    </properties>
                    <required>False</required>
                    <rules>[]</rules>
                    <show_for_rule>True</show_for_rule>
                    <validations>{}</validations>
                    <visible>True</visible>
                </item>
                <item>
                    <affecting_rules>[]</affecting_rules>
                    <buttons_ids>[]</buttons_ids>
                    <catalog>None</catalog>
                    <catalog_fields>[]</catalog_fields>
                    <catalog_relation>None</catalog_relation>
                    <default>False</default>
                    <default_value />
                    <descriptor>None</descriptor>
                    <fav>False</fav>
                    <field_id>6318d363a76a4d7dd439b87d</field_id>
                    <field_type>checkbox</field_type>
                    <grading_criteria>{}</grading_criteria>
                    <group>
                        <group_id>6318d2dc0d37da73390c3d1d</group_id>
                        <group_set_id>0</group_set_id>
                    </group>
                    <groups_fields>[]</groups_fields>
                    <help_text>None</help_text>
                    <label>Aplica en</label>
                    <number_type>None</number_type>
                    <options>
                        <item>
                            <label>Orden Compra CONTRATISTA FTTH - METRO (19620)</label>
                            <points>None</points>
                            <selected>False</selected>
                            <value>orden_compra_contratista_ftth_-_metro_(19620)</value>
                        </item>
                        <item>
                            <label>Orden Compra CONTRATISTA FTTH - SUR (44672)</label>
                            <points>None</points>
                            <selected>False</selected>
                            <value>orden_compra_contratista_ftth_-_sur_(44672)</value>
                        </item>
                        <item>
                            <label>Orden Compra CONTRATISTA FTTH - NORTE (50778)</label>
                            <points>None</points>
                            <selected>False</selected>
                            <value>orden_compra_contratista_ftth_-_norte_(50778)</value>
                        </item>
                        <item>
                            <label>Orden Compra CONTRATISTA FTTH - OCCIDENTE (50594)</label>
                            <points>None</points>
                            <selected>False</selected>
                            <value>orden_compra_contratista_ftth_-_occidente_(50594)</value>
                        </item>
                        <item>
                            <label>Orden Compra CONTRATISTA COBRE - METRO (33658)</label>
                            <points>None</points>
                            <selected>False</selected>
                            <value>orden_compra_contratista_cobre_-_metro_(33658)</value>
                        </item>
                        <item>
                            <label>Orden Compra CONTRATISTA COBRE - SUR (45420)</label>
                            <points>None</points>
                            <selected>False</selected>
                            <value>orden_compra_contratista_cobre_-_sur_(45420)</value>
                        </item>
                        <item>
                            <label>Orden Compra CONTRATISTA COBRE - NORTE (50779)</label>
                            <points>None</points>
                            <selected>False</selected>
                            <value>orden_compra_contratista_cobre_-_norte_(50779)</value>
                        </item>
                        <item>
                            <label>Orden Compra CONTRATISTA COBRE - OCCIDENTE (50595)</label>
                            <points>None</points>
                            <selected>False</selected>
                            <value>orden_compra_contratista_cobre_-_occidente_(50595)</value>
                        </item>
                        <item>
                            <label>ORDEN DE COMPRA CONTRATISTA - FIELDERS (66030)</label>
                            <points>None</points>
                            <selected>False</selected>
                            <value>orden_de_compra_contratista_-_fielders_(66030)</value>
                        </item>
                        <item>
                            <label>Estimación Proyectos Especiales (66948)</label>
                            <points>None</points>
                            <selected>False</selected>
                            <value>estimación_proyectos_especiales_(66948)</value>
                        </item>
                        <item>
                            <label>Factura Remanente (79069)</label>
                            <points>None</points>
                            <selected>False</selected>
                            <value>factura_remanente_(79069)</value>
                        </item>
                        <item>
                            <label>Orden Compra CONTRATISTA FTTH - CFE Linea (91686)</label>
                            <points>None</points>
                            <selected>False</selected>
                            <value>orden_compra_contratista_ftth_-_cfe_linea_(91686)</value>
                        </item>
                        <item>
                            <label>Orden Compra CONTRATISTA COBRE - CFE Linea (91685)</label>
                            <points>None</points>
                            <selected>False</selected>
                            <value>orden_compra_contratista_cobre_-_cfe_linea_(91685)</value>
                        </item>
                        <item>
                            <label>Orden Compra CONTRATISTA COBRE - CFE Antena (91688)</label>
                            <points>None</points>
                            <selected>False</selected>
                            <value>orden_compra_contratista_cobre_-_cfe_antena_(91688)</value>
                        </item>
                        <item>
                            <label>Orden Compra CONTRATISTA FTTH - CFE Antena (91687)</label>
                            <points>None</points>
                            <selected>False</selected>
                            <value>orden_compra_contratista_ftth_-_cfe_antena_(91687)</value>
                        </item>
                        <item>
                            <label>Facturación General (102610)</label>
                            <points>None</points>
                            <selected>False</selected>
                            <value>facturación_general_(102610)</value>
                        </item>
                    </options>
                    <properties>
                        <body_payload>[]</body_payload>
                        <color />
                        <comment />
                        <custom />
                        <elements_ids>[]</elements_ids>
                        <email_configuration>None</email_configuration>
                        <enable_barcode>None</enable_barcode>
                        <fieldId>[]</fieldId>
                        <file_name />
                        <file_name_array>[]</file_name_array>
                        <help_text>False</help_text>
                        <icon>{}</icon>
                        <image_origin>None</image_origin>
                        <input_parameter>[]</input_parameter>
                        <max>None</max>
                        <max_images_count>5</max_images_count>
                        <metadata>[]</metadata>
                        <method />
                        <mime_types>[]</mime_types>
                        <min>None</min>
                        <min_images_count>0</min_images_count>
                        <multi_selection>False</multi_selection>
                        <notification>{}</notification>
                        <number_of_decimals>2</number_of_decimals>
                        <openChoice>False</openChoice>
                        <parameters>[]</parameters>
                        <pfd_print>always</pfd_print>
                        <pfd_style>Tabla_respuestas</pfd_style>
                        <selected>0</selected>
                        <send_email>False</send_email>
                        <send_record>False</send_record>
                        <send_to_lkf>False</send_to_lkf>
                        <service_name />
                        <update_values>{}</update_values>
                        <url />
                        <username>False</username>
                        <visible_on />
                        <wait_response>False</wait_response>
                        <watermark_config>None</watermark_config>
                        <watermark_enable>False</watermark_enable>
                    </properties>
                    <required>False</required>
                    <rules>[]</rules>
                    <show_for_rule>True</show_for_rule>
                    <validations>{}</validations>
                    <visible>True</visible>
                </item>
                <item>
                    <affecting_rules>[]</affecting_rules>
                    <buttons_ids>[]</buttons_ids>
                    <catalog>None</catalog>
                    <catalog_fields>[]</catalog_fields>
                    <catalog_relation>None</catalog_relation>
                    <default>False</default>
                    <default_value />
                    <descriptor>None</descriptor>
                    <fav>False</fav>
                    <field_id>6475297f252ea20a2916a9d5</field_id>
                    <field_type>checkbox</field_type>
                    <grading_criteria>{}</grading_criteria>
                    <group>
                        <group_id>6318d2dc0d37da73390c3d1d</group_id>
                        <group_set_id>0</group_set_id>
                    </group>
                    <groups_fields>[]</groups_fields>
                    <help_text>None</help_text>
                    <label>Proyecto</label>
                    <number_type>None</number_type>
                    <options>
                        <item>
                            <label>Mantenimiento de terminales</label>
                            <points>None</points>
                            <selected>False</selected>
                            <value>mantenimiento_de_terminales</value>
                        </item>
                        <item>
                            <label>Entradas 50 (redes)</label>
                            <points>None</points>
                            <selected>False</selected>
                            <value>entradas_50_(redes)</value>
                        </item>
                        <item>
                            <label>Entradas 50 (redes) ANTICIPO</label>
                            <points>None</points>
                            <selected>False</selected>
                            <value>entradas_50_(redes)_anticipo</value>
                        </item>
                        <item>
                            <label>Proveedores</label>
                            <points>None</points>
                            <selected>False</selected>
                            <value>proveedores</value>
                        </item>
                        <item>
                            <label>Telcel Infraestructura (FACTURA)</label>
                            <points>None</points>
                            <selected>False</selected>
                            <value>telcel_infraestructura_(factura)</value>
                        </item>
                        <item>
                            <label>Telcel Infraestructura (ANTICIPO)</label>
                            <points>None</points>
                            <selected>False</selected>
                            <value>telcel_infraestructura_(anticipo)</value>
                        </item>
                        <item>
                            <label>Telcel Infraestructura (SUPERVISIÓN)</label>
                            <points>None</points>
                            <selected>False</selected>
                            <value>telcel_infraestructura_(supervisión)</value>
                        </item>
                        <item>
                            <label>Telesites (FACTURA)</label>
                            <points>None</points>
                            <selected>False</selected>
                            <value>telesites_(factura)</value>
                        </item>
                        <item>
                            <label>Telesites (ANTICIPO)</label>
                            <points>None</points>
                            <selected>False</selected>
                            <value>telesites_(anticipo)</value>
                        </item>
                        <item>
                            <label>Limpieza e Imagen (FACTURA)</label>
                            <points>None</points>
                            <selected>False</selected>
                            <value>limpieza_e_imagen_(factura)</value>
                        </item>
                        <item>
                            <label>Limpieza e Imagen (ANTICIPO)</label>
                            <points>None</points>
                            <selected>False</selected>
                            <value>limpieza_e_imagen_(anticipo)</value>
                        </item>
                        <item>
                            <label>Mecánicos</label>
                            <points>None</points>
                            <selected>False</selected>
                            <value>mecánicos</value>
                        </item>
                        <item>
                            <label>Mantenimiento Inmuebles Telcel</label>
                            <points>None</points>
                            <selected>False</selected>
                            <value>mantenimiento_inmuebles_telcel</value>
                        </item>
                        <item>
                            <label>Emergencias Inmuebles Telcel</label>
                            <points>None</points>
                            <selected>False</selected>
                            <value>emergencias_inmuebles_telcel</value>
                        </item>
                        <item>
                            <label>Materiales Inmuebles Telcel</label>
                            <points>None</points>
                            <selected>False</selected>
                            <value>materiales_inmuebles_telcel</value>
                        </item>
                        <item>
                            <label>Correctivos y Concursos Inmuebles Telcel</label>
                            <points>None</points>
                            <selected>False</selected>
                            <value>correctivos_y_concursos_inmuebles_telcel</value>
                        </item>
                        <item>
                            <label>Jardinería Inmuebles Telcel</label>
                            <points>None</points>
                            <selected>False</selected>
                            <value>jardinería_inmuebles_telcel</value>
                        </item>
                        <item>
                            <label>Fibra (ANTICIPO)</label>
                            <points>None</points>
                            <selected>False</selected>
                            <value>fibra_(anticipo)</value>
                        </item>
                    </options>
                    <properties>
                        <body_payload>[]</body_payload>
                        <color />
                        <comment />
                        <custom />
                        <elements_ids>[]</elements_ids>
                        <email_configuration>None</email_configuration>
                        <enable_barcode>None</enable_barcode>
                        <fieldId>[]</fieldId>
                        <file_name />
                        <file_name_array>[]</file_name_array>
                        <help_text>False</help_text>
                        <icon>{}</icon>
                        <image_origin>None</image_origin>
                        <input_parameter>[]</input_parameter>
                        <max>None</max>
                        <max_images_count>5</max_images_count>
                        <metadata>[]</metadata>
                        <method />
                        <mime_types>[]</mime_types>
                        <min>None</min>
                        <min_images_count>0</min_images_count>
                        <multi_selection>False</multi_selection>
                        <notification>{}</notification>
                        <number_of_decimals>2</number_of_decimals>
                        <openChoice>False</openChoice>
                        <parameters>[]</parameters>
                        <pfd_print>always</pfd_print>
                        <pfd_style>Tabla_respuestas</pfd_style>
                        <selected>0</selected>
                        <send_email>False</send_email>
                        <send_record>False</send_record>
                        <send_to_lkf>False</send_to_lkf>
                        <service_name />
                        <update_values>{}</update_values>
                        <url />
                        <username>False</username>
                        <visible_on />
                        <wait_response>False</wait_response>
                        <watermark_config>None</watermark_config>
                        <watermark_enable>False</watermark_enable>
                    </properties>
                    <required>False</required>
                    <rules>[]</rules>
                    <show_for_rule>True</show_for_rule>
                    <validations>{}</validations>
                    <visible>True</visible>
                </item>
                <item>
                    <affecting_rules>[]</affecting_rules>
                    <buttons_ids>[]</buttons_ids>
                    <catalog>None</catalog>
                    <catalog_fields>[]</catalog_fields>
                    <catalog_relation>None</catalog_relation>
                    <default>False</default>
                    <default_value />
                    <descriptor>None</descriptor>
                    <fav>False</fav>
                    <field_id>6318d157e7dc26b52f2c4293</field_id>
                    <field_type>text</field_type>
                    <grading_criteria>{}</grading_criteria>
                    <group>
                        <group_id>6318d13144b1e9292d39b8b5</group_id>
                        <group_set_id>0</group_set_id>
                    </group>
                    <groups_fields>[]</groups_fields>
                    <help_text>None</help_text>
                    <label>Principal</label>
                    <number_type>None</number_type>
                    <options>[]</options>
                    <properties>
                        <body_payload>[]</body_payload>
                        <color />
                        <comment />
                        <custom />
                        <elements_ids>[]</elements_ids>
                        <email_configuration>None</email_configuration>
                        <enable_barcode>None</enable_barcode>
                        <fieldId>[]</fieldId>
                        <file_name />
                        <file_name_array>[]</file_name_array>
                        <help_text>False</help_text>
                        <icon>{}</icon>
                        <image_origin>None</image_origin>
                        <input_parameter>[]</input_parameter>
                        <max>None</max>
                        <max_images_count>5</max_images_count>
                        <metadata>[]</metadata>
                        <method />
                        <mime_types>[]</mime_types>
                        <min>None</min>
                        <min_images_count>0</min_images_count>
                        <multi_selection>False</multi_selection>
                        <notification>{}</notification>
                        <number_of_decimals>2</number_of_decimals>
                        <openChoice>False</openChoice>
                        <parameters>[]</parameters>
                        <pfd_print>always</pfd_print>
                        <pfd_style>Tabla_respuestas</pfd_style>
                        <selected>None</selected>
                        <send_email>False</send_email>
                        <send_record>False</send_record>
                        <send_to_lkf>False</send_to_lkf>
                        <service_name />
                        <update_values>{}</update_values>
                        <url />
                        <username>False</username>
                        <visible_on />
                        <wait_response>False</wait_response>
                        <watermark_config>None</watermark_config>
                        <watermark_enable>False</watermark_enable>
                    </properties>
                    <required>True</required>
                    <rules>[]</rules>
                    <show_for_rule>True</show_for_rule>
                    <validations>{}</validations>
                    <visible>True</visible>
                </item>
                <item>
                    <affecting_rules>[]</affecting_rules>
                    <buttons_ids>[]</buttons_ids>
                    <catalog>None</catalog>
                    <catalog_fields>[]</catalog_fields>
                    <catalog_relation>None</catalog_relation>
                    <default>False</default>
                    <default_value />
                    <descriptor>None</descriptor>
                    <fav>False</fav>
                    <field_id>6318d2136217e6d71339b8c1</field_id>
                    <field_type>textarea</field_type>
                    <grading_criteria>{}</grading_criteria>
                    <group>
                        <group_id>6318d13144b1e9292d39b8b5</group_id>
                        <group_set_id>0</group_set_id>
                    </group>
                    <groups_fields>[]</groups_fields>
                    <help_text>None</help_text>
                    <label>Variantes</label>
                    <number_type>None</number_type>
                    <options>[]</options>
                    <properties>
                        <body_payload>[]</body_payload>
                        <color />
                        <comment />
                        <custom />
                        <elements_ids>[]</elements_ids>
                        <email_configuration>None</email_configuration>
                        <enable_barcode>None</enable_barcode>
                        <fieldId>[]</fieldId>
                        <file_name />
                        <file_name_array>[]</file_name_array>
                        <help_text>False</help_text>
                        <icon>{}</icon>
                        <image_origin>None</image_origin>
                        <input_parameter>[]</input_parameter>
                        <max>None</max>
                        <max_images_count>5</max_images_count>
                        <metadata>[]</metadata>
                        <method />
                        <mime_types>[]</mime_types>
                        <min>None</min>
                        <min_images_count>0</min_images_count>
                        <multi_selection>False</multi_selection>
                        <notification>{}</notification>
                        <number_of_decimals>2</number_of_decimals>
                        <openChoice>False</openChoice>
                        <parameters>[]</parameters>
                        <pfd_print>always</pfd_print>
                        <pfd_style>Tabla_respuestas</pfd_style>
                        <selected>None</selected>
                        <send_email>False</send_email>
                        <send_record>False</send_record>
                        <send_to_lkf>False</send_to_lkf>
                        <service_name />
                        <update_values>{}</update_values>
                        <url />
                        <username>False</username>
                        <visible_on />
                        <wait_response>False</wait_response>
                        <watermark_config>None</watermark_config>
                        <watermark_enable>False</watermark_enable>
                    </properties>
                    <required>False</required>
                    <rules>[]</rules>
                    <show_for_rule>True</show_for_rule>
                    <validations>{}</validations>
                    <visible>True</visible>
                </item>
                <item>
                    <affecting_rules>[]</affecting_rules>
                    <buttons_ids>[]</buttons_ids>
                    <catalog>None</catalog>
                    <catalog_fields>[]</catalog_fields>
                    <catalog_relation>None</catalog_relation>
                    <default>False</default>
                    <default_value />
                    <descriptor>None</descriptor>
                    <fav>False</fav>
                    <field_id>6318d2136217e6d71339b8c2</field_id>
                    <field_type>textarea</field_type>
                    <grading_criteria>{}</grading_criteria>
                    <group>
                        <group_id>6318d13144b1e9292d39b8b5</group_id>
                        <group_set_id>0</group_set_id>
                    </group>
                    <groups_fields>[]</groups_fields>
                    <help_text>None</help_text>
                    <label>RFC's</label>
                    <number_type>None</number_type>
                    <options>[]</options>
                    <properties>
                        <body_payload>[]</body_payload>
                        <color />
                        <comment />
                        <custom />
                        <elements_ids>[]</elements_ids>
                        <email_configuration>None</email_configuration>
                        <enable_barcode>None</enable_barcode>
                        <fieldId>[]</fieldId>
                        <file_name />
                        <file_name_array>[]</file_name_array>
                        <help_text>False</help_text>
                        <icon>{}</icon>
                        <image_origin>None</image_origin>
                        <input_parameter>[]</input_parameter>
                        <max>None</max>
                        <max_images_count>5</max_images_count>
                        <metadata>[]</metadata>
                        <method />
                        <mime_types>[]</mime_types>
                        <min>None</min>
                        <min_images_count>0</min_images_count>
                        <multi_selection>False</multi_selection>
                        <notification>{}</notification>
                        <number_of_decimals>2</number_of_decimals>
                        <openChoice>False</openChoice>
                        <parameters>[]</parameters>
                        <pfd_print>always</pfd_print>
                        <pfd_style>Tabla_respuestas</pfd_style>
                        <selected>None</selected>
                        <send_email>False</send_email>
                        <send_record>False</send_record>
                        <send_to_lkf>False</send_to_lkf>
                        <service_name />
                        <update_values>{}</update_values>
                        <url />
                        <username>False</username>
                        <visible_on />
                        <wait_response>False</wait_response>
                        <watermark_config>None</watermark_config>
                        <watermark_enable>False</watermark_enable>
                    </properties>
                    <required>True</required>
                    <rules>[]</rules>
                    <show_for_rule>True</show_for_rule>
                    <validations>{}</validations>
                    <visible>True</visible>
                </item>
                <item>
                    <affecting_rules>[]</affecting_rules>
                    <buttons_ids>[]</buttons_ids>
                    <catalog>None</catalog>
                    <catalog_fields>[]</catalog_fields>
                    <catalog_relation>None</catalog_relation>
                    <default>False</default>
                    <default_value />
                    <descriptor>None</descriptor>
                    <fav>False</fav>
                    <field_id>6318d2136217e6d71339b8c3</field_id>
                    <field_type>checkbox</field_type>
                    <grading_criteria>{}</grading_criteria>
                    <group>
                        <group_id>6318d13144b1e9292d39b8b5</group_id>
                        <group_set_id>0</group_set_id>
                    </group>
                    <groups_fields>[]</groups_fields>
                    <help_text>None</help_text>
                    <label>Aplica en</label>
                    <number_type>None</number_type>
                    <options>
                        <item>
                            <label>Orden Compra CONTRATISTA FTTH - METRO (19620)</label>
                            <points>None</points>
                            <selected>False</selected>
                            <value>orden_compra_contratista_ftth_-_metro_(19620)</value>
                        </item>
                        <item>
                            <label>Orden Compra CONTRATISTA FTTH - SUR (44672)</label>
                            <points>None</points>
                            <selected>False</selected>
                            <value>orden_compra_contratista_ftth_-_sur_(44672)</value>
                        </item>
                        <item>
                            <label>Orden Compra CONTRATISTA FTTH - NORTE (50778)</label>
                            <points>None</points>
                            <selected>False</selected>
                            <value>orden_compra_contratista_ftth_-_norte_(50778)</value>
                        </item>
                        <item>
                            <label>Orden Compra CONTRATISTA FTTH - OCCIDENTE (50594)</label>
                            <points>None</points>
                            <selected>False</selected>
                            <value>orden_compra_contratista_ftth_-_occidente_(50594)</value>
                        </item>
                        <item>
                            <label>Orden Compra CONTRATISTA COBRE - METRO (33658)</label>
                            <points>None</points>
                            <selected>False</selected>
                            <value>orden_compra_contratista_cobre_-_metro_(33658)</value>
                        </item>
                        <item>
                            <label>Orden Compra CONTRATISTA COBRE - SUR (45420)</label>
                            <points>None</points>
                            <selected>False</selected>
                            <value>orden_compra_contratista_cobre_-_sur_(45420)</value>
                        </item>
                        <item>
                            <label>Orden Compra CONTRATISTA COBRE - NORTE (50779)</label>
                            <points>None</points>
                            <selected>False</selected>
                            <value>orden_compra_contratista_cobre_-_norte_(50779)</value>
                        </item>
                        <item>
                            <label>Orden Compra CONTRATISTA COBRE - OCCIDENTE (50595)</label>
                            <points>None</points>
                            <selected>False</selected>
                            <value>orden_compra_contratista_cobre_-_occidente_(50595)</value>
                        </item>
                        <item>
                            <label>ORDEN DE COMPRA CONTRATISTA - FIELDERS (66030)</label>
                            <points>None</points>
                            <selected>False</selected>
                            <value>orden_de_compra_contratista_-_fielders_(66030)</value>
                        </item>
                        <item>
                            <label>Factura Remanente (79069)</label>
                            <points>None</points>
                            <selected>False</selected>
                            <value>factura_remanente_(79069)</value>
                        </item>
                        <item>
                            <label>Estimación Proyectos Especiales (66948)</label>
                            <points>None</points>
                            <selected>False</selected>
                            <value>estimación_proyectos_especiales_(66948)</value>
                        </item>
                        <item>
                            <label>Orden Compra CONTRATISTA FTTH - CFE Linea (91686)</label>
                            <points>None</points>
                            <selected>False</selected>
                            <value>orden_compra_contratista_ftth_-_cfe_linea_(91686)</value>
                        </item>
                        <item>
                            <label>Orden Compra CONTRATISTA COBRE - CFE Linea (91685)</label>
                            <points>None</points>
                            <selected>False</selected>
                            <value>orden_compra_contratista_cobre_-_cfe_linea_(91685)</value>
                        </item>
                        <item>
                            <label>Orden Compra CONTRATISTA COBRE - CFE Antena (91688)</label>
                            <points>None</points>
                            <selected>False</selected>
                            <value>orden_compra_contratista_cobre_-_cfe_antena_(91688)</value>
                        </item>
                        <item>
                            <label>Orden Compra CONTRATISTA FTTH - CFE Antena (91687)</label>
                            <points>None</points>
                            <selected>False</selected>
                            <value>orden_compra_contratista_ftth_-_cfe_antena_(91687)</value>
                        </item>
                        <item>
                            <label>Facturación General (102610)</label>
                            <points>None</points>
                            <selected>False</selected>
                            <value>facturación_general_(102610)</value>
                        </item>
                        <item>
                            <label>Orden Compra CONTRATISTA - PSR (125625)</label>
                            <points>None</points>
                            <selected>False</selected>
                            <value>orden_compra_contratista_-_psr_(125625)</value>
                        </item>
                    </options>
                    <properties>
                        <body_payload>[]</body_payload>
                        <color />
                        <comment />
                        <custom />
                        <elements_ids>[]</elements_ids>
                        <email_configuration>None</email_configuration>
                        <enable_barcode>None</enable_barcode>
                        <fieldId>[]</fieldId>
                        <file_name />
                        <file_name_array>[]</file_name_array>
                        <help_text>False</help_text>
                        <icon>{}</icon>
                        <image_origin>None</image_origin>
                        <input_parameter>[]</input_parameter>
                        <max>None</max>
                        <max_images_count>5</max_images_count>
                        <metadata>[]</metadata>
                        <method />
                        <mime_types>[]</mime_types>
                        <min>None</min>
                        <min_images_count>0</min_images_count>
                        <multi_selection>False</multi_selection>
                        <notification>{}</notification>
                        <number_of_decimals>2</number_of_decimals>
                        <openChoice>False</openChoice>
                        <parameters>[]</parameters>
                        <pfd_print>always</pfd_print>
                        <pfd_style>Tabla_respuestas</pfd_style>
                        <selected>0</selected>
                        <send_email>False</send_email>
                        <send_record>False</send_record>
                        <send_to_lkf>False</send_to_lkf>
                        <service_name />
                        <update_values>{}</update_values>
                        <url />
                        <username>False</username>
                        <visible_on />
                        <wait_response>False</wait_response>
                        <watermark_config>None</watermark_config>
                        <watermark_enable>False</watermark_enable>
                    </properties>
                    <required>False</required>
                    <rules>[]</rules>
                    <show_for_rule>True</show_for_rule>
                    <validations>{}</validations>
                    <visible>True</visible>
                </item>
            </page_fields>
            <page_name>Página 1</page_name>
            <page_type>fields</page_type>
        </item>
    </form_pages>
    <grading>
        <active>False</active>
        <grade_type>points</grade_type>
        <max_points>0</max_points>
    </grading>
    <has_voucher>False</has_voucher>
    <name>Configuración de validaciones</name>
    <notification>
        <active>False</active>
    </notification>
    <process_ids>[]</process_ids>
    <public>False</public>
    <resource_uri>/api/infosync/form/89381/</resource_uri>
    <send_on_foreground>False</send_on_foreground>
    <start_event_id>None</start_event_id>
    <template_conf>
        <account_id>None</account_id>
        <configuration>{}</configuration>
        <is_master>True</is_master>
        <is_public>False</is_public>
        <master_id>None</master_id>
        <name />
        <unify_ids>False</unify_ids>
    </template_conf>
    <templates>[]</templates>
    <timer_config>
        <active>False</active>
        <clicks_to_expire>None</clicks_to_expire>
        <goodbye_text>None</goodbye_text>
        <minutes>None</minutes>
        <seconds_to_expire>None</seconds_to_expire>
        <welcome_text>None</welcome_text>
    </timer_config>
    <updated_at>1733848615.0</updated_at>
</lkf>